Classifier/__init__.py
Classifier/classify.py
Classifier/config.py
Classifier/merge.py
Classify/__init__.py
Classify/classify.py
Classify/config.py
Classify/merge.py
file_classifier-0.1.0.dist-info/LICENSE
file_classifier-0.1.0.dist-info/METADATA
file_classifier-0.1.0.dist-info/WHEEL
file_classifier-0.1.0.dist-info/entry_points.txt
file_classifier-0.1.0.dist-info/top_level.txt
file_classifier-0.1.0.dist-info/RECORD
