Metadata-Version: 2.1
Name: file-classifier
Version: 0.1.0
Summary: A simple classifier to manage your messy desktop files.
Home-page: https://github.com/T0nyX1ang/Classifier
Author: Tony Xiang
Author-email: tonyxfy@qq.com
License: UNKNOWN
Keywords: File Management,Classification
Platform: all
Classifier: Development Status :: 3 - Alpha
Classifier: Programming Language :: Python :: 3.5
Classifier: Programming Language :: Python :: 3.6
Classifier: Programming Language :: Python :: 3.7
Classifier: Programming Language :: Python :: 3.8
Classifier: Environment :: Console
Classifier: License :: OSI Approved :: MIT License
Classifier: Operating System :: OS Independent
